unixgroups/__init__.py
unixgroups/unixgroups.py
TracUnixGroups-0.2.dist-info/METADATA
TracUnixGroups-0.2.dist-info/WHEEL
TracUnixGroups-0.2.dist-info/entry_points.txt
TracUnixGroups-0.2.dist-info/top_level.txt
TracUnixGroups-0.2.dist-info/RECORD
